nornir_infrahub/__init__.py
nornir_infrahub/plugins/inventory/infrahub.py
nornir_infrahub/plugins/tasks/__init__.py
nornir_infrahub/plugins/tasks/artifact.py
nornir_infrahub-1.1.2.dist-info/METADATA
nornir_infrahub-1.1.2.dist-info/WHEEL
nornir_infrahub-1.1.2.dist-info/entry_points.txt
nornir_infrahub-1.1.2.dist-info/licenses/LICENSE.txt
nornir_infrahub-1.1.2.dist-info/RECORD
