Metadata-Version: 2.4
Name: nornir-infrahub
Version: 1.1.2
Summary: Nornir plugin for Infrahub
License: Apache-2.0
License-File: LICENSE.txt
Author: OpsMill
Author-email: info@opsmill.com
Requires-Python: >=3.9,<3.13
Classifier: Intended Audience :: Developers
Classifier: License :: OSI Approved :: Apache Software License
Classifier: Programming Language :: Python :: 3
Classifier: Programming Language :: Python :: 3.9
Classifier: Programming Language :: Python :: 3.10
Classifier: Programming Language :: Python :: 3.11
Classifier: Programming Language :: Python :: 3.12
Requires-Dist: infrahub-sdk[tests] (>=1.3.0,<2)
Requires-Dist: nornir (>=3.5,<4.0)
Requires-Dist: nornir-utils (>=0.2.0,<0.3.0)
Requires-Dist: pydantic (>=1.7.4,!=1.8,!=1.8.1,!=2.0.0,!=2.0.1,!=2.1.0,<3.0.0)
Requires-Dist: python-slugify (>=8.0.1,<9.0.0)
Requires-Dist: ruamel-yaml (>=0.18.5,<0.19.0)
Project-URL: Documentation, https://docs.infrahub.app/
Project-URL: Homepage, https://opsmill.com
Project-URL: Repository, https://github.com/opsmill/nornir-infrahub
